{
  "parent": "minecraft:recipes/root",
  "criteria": {
    "has_ender_block": {
      "conditions": {
        "items": [
          {
            "items": [
              "blocks_of_monster_stuff:ender_block"
            ]
          }
        ]
      },
      "trigger": "minecraft:inventory_changed"
    },
    "has_the_recipe": {
      "conditions": {
        "recipe": "minecraft:ender_pearl_from_ender_block"
      },
      "trigger": "minecraft:recipe_unlocked"
    }
  },
  "requirements": [
    [
      "has_the_recipe",
      "has_ender_block"
    ]
  ],
  "rewards": {
    "recipes": [
      "minecraft:ender_pearl_from_ender_block"
    ]
  }
}